rollplayerlib/__init__.py
rollplayerlib/bonuses.py
rollplayerlib/config.py
rollplayerlib/dice.py
rollplayerlib/enums.py
rollplayerlib/exceptions.py
rollplayerlib/formatting.py
rollplayerlib-0.5.11.0.0.0.0.0.0.0.0.0.0.0.1.dist-info/LICENSE
rollplayerlib-0.5.11.0.0.0.0.0.0.0.0.0.0.0.1.dist-info/METADATA
rollplayerlib-0.5.11.0.0.0.0.0.0.0.0.0.0.0.1.dist-info/WHEEL
rollplayerlib-0.5.11.0.0.0.0.0.0.0.0.0.0.0.1.dist-info/top_level.txt
rollplayerlib-0.5.11.0.0.0.0.0.0.0.0.0.0.0.1.dist-info/RECORD
