Metadata-Version: 2.2
Name: rollplayerlib
Version: 0.5.11.0.0.0.0.0.0.0.0.0.0.0.1
Summary: A library to roll dice in a simple way, but with advanced functionality.
Author-email: whirlingstars <infernity@infernity.dev>
License: MIT
Keywords: DICE,ROLL,RANDOM
Classifier: Development Status :: 4 - Beta
Classifier: Intended Audience :: Developers
Classifier: License :: OSI Approved :: MIT License
Classifier: Programming Language :: Python :: 3
Classifier: Programming Language :: Python :: 3.10
Classifier: Programming Language :: Python :: 3.11
Classifier: Programming Language :: Python :: 3.12
License-File: LICENSE
